scrape_schema/__init__.py
scrape_schema/_logger.py
scrape_schema/_protocols.py
scrape_schema/_typing.py
scrape_schema/base.py
scrape_schema/exceptions.py
scrape_schema/field.py
scrape_schema/nested.py
scrape_schema/type_caster.py
scrape_schema/validator.py
scrape_schema/codegen/__init__.py
scrape_schema/codegen/codegen.py
scrape_schema/codegen/constants.py
scrape_schema/codegen/pydantic.py
scrape_schema/codegen/utils.py
scrape_schema/codegen/templates/pydantic.j2
scrape_schema/codegen/templates/pydantic_sub_model.j2
scrape_schema/special_methods/__init__.py
scrape_schema/special_methods/base.py
scrape_schema/special_methods/methods.py
scrape_schema-0.6.3.dist-info/METADATA
scrape_schema-0.6.3.dist-info/WHEEL
scrape_schema-0.6.3.dist-info/licenses/LICENSE
scrape_schema-0.6.3.dist-info/RECORD
