Metadata-Version: 2.1
Name: scrape-schema
Version: 0.6.3
Summary: A library for converting any text (xml, html, plain text, stdout, etc) to python datatypes
Project-URL: Documentation, https://github.com/vypivshiy/scrape-schema#readme
Project-URL: Issues, https://github.com/vypivshiy/scrape-schema/issues
Project-URL: Source, https://github.com/vypivshiy/scrape-schema
Project-URL: Examples, https://github.com/vypivshiy/scrape-schema/examples
Author: vypivshiy
License-Expression: MIT
License-File: LICENSE
Classifier: Development Status :: 3 - Alpha
Classifier: Programming Language :: Python
Classifier: Programming Language :: Python :: 3.8
Classifier: Programming Language :: Python :: 3.9
Classifier: Programming Language :: Python :: 3.10
Classifier: Programming Language :: Python :: 3.11
Classifier: Programming Language :: Python :: Implementation :: CPython
Classifier: Programming Language :: Python :: Implementation :: PyPy
Classifier: Topic :: Internet
Classifier: Topic :: Software Development :: Libraries :: Python Modules
Classifier: Topic :: Text Processing
Requires-Python: >=3.8
Requires-Dist: chompjs
Requires-Dist: colorlog
Requires-Dist: parsel
Requires-Dist: typing-extensions; python_version < '3.11'
Provides-Extra: ci
Requires-Dist: black; extra == 'ci'
Requires-Dist: hatch; extra == 'ci'
Requires-Dist: isort; extra == 'ci'
Requires-Dist: mypy; extra == 'ci'
Requires-Dist: parsel; extra == 'ci'
Requires-Dist: pytest; extra == 'ci'
Requires-Dist: ruff; extra == 'ci'
Provides-Extra: codegen
Requires-Dist: jinja2; extra == 'codegen'
Provides-Extra: dev
Requires-Dist: black; extra == 'dev'
Requires-Dist: hatch; extra == 'dev'
Requires-Dist: isort; extra == 'dev'
Requires-Dist: mypy; extra == 'dev'
Requires-Dist: pre-commit; extra == 'dev'
Requires-Dist: pytest; extra == 'dev'
Requires-Dist: ruff; extra == 'dev'
Provides-Extra: docs
Requires-Dist: mkdocs-material; extra == 'docs'
Requires-Dist: mkdocstrings[python]; extra == 'docs'
